MANIFEST.in
hr_payroll_account_demo.xml
hr_payroll_account_view.xml
setup.py
./__init__.py
./__openerp__.py
./hr_payroll_account.py
./wizard/__init__.py
./wizard/hr_payroll_payslips_by_employees.py
i18n/ar.po
i18n/bg.po
i18n/ca.po
i18n/cs.po
i18n/da.po
i18n/de.po
i18n/en_GB.po
i18n/es.po
i18n/es_CR.po
i18n/es_EC.po
i18n/es_MX.po
i18n/es_PY.po
i18n/es_VE.po
i18n/fr.po
i18n/gl.po
i18n/gu.po
i18n/hr.po
i18n/hr_payroll_account.pot
i18n/hu.po
i18n/id.po
i18n/it.po
i18n/ja.po
i18n/lt.po
i18n/lv.po
i18n/mk.po
i18n/mn.po
i18n/nb.po
i18n/nl.po
i18n/pl.po
i18n/pt.po
i18n/pt_BR.po
i18n/ro.po
i18n/ru.po
i18n/sl.po
i18n/sr@latin.po
i18n/sv.po
i18n/tr.po
i18n/zh_CN.po
i18n/zh_TW.po
images/hr_employee_payslip.jpeg
openerp_hr_payroll_account.egg-info/PKG-INFO
openerp_hr_payroll_account.egg-info/SOURCES.txt
openerp_hr_payroll_account.egg-info/dependency_links.txt
openerp_hr_payroll_account.egg-info/requires.txt
openerp_hr_payroll_account.egg-info/top_level.txt
test/hr_payroll_account.yml